setup.py
persona_test_user/__init__.py
persona_test_user/persona_test_user.py
persona_test_user.egg-info/PKG-INFO
persona_test_user.egg-info/SOURCES.txt
persona_test_user.egg-info/dependency_links.txt
persona_test_user.egg-info/top_level.txt