Metadata-Version: 1.0
Name: persona-test-user
Version: 0.1
Summary: Generate Persona Test Accounts
Home-page: https://github.com/bebef1987/persona-test-user
Author: Florin Strugariu, Zac Campbell
Author-email: bebe@mozilla.ro
License: Mozilla Public License 2.0 (MPL 2.0)
Platform: UNKNOWN
